{"trial_id": "06", "hyperparameters": {"space": [{"class_name": "Choice", "config": {"name": "optimizer", "default": "adam", "conditions": [], "values": ["adam", "sgd"], "ordered": false}}, {"class_name": "Float", "config": {"name": "learning_rate", "default": 1e-05, "conditions": [], "min_value": 1e-05, "max_value": 0.1, "step": null, "sampling": "log"}}], "values": {"optimizer": "adam", "learning_rate": 0.0024233945470565474}}, "metrics": {"metrics": {"accuracy": {"direction": "max", "observations": [{"value": [0.5634999871253967], "step": 9}]}, "loss": {"direction": "min", "observations": [{"value": [1.2248708009719849], "step": 9}]}, "val_accuracy": {"direction": "max", "observations": [{"value": [0.6294999718666077], "step": 9}]}, "val_loss": {"direction": "min", "observations": [{"value": [1.0378079414367676], "step": 9}]}}}, "score": 0.6294999718666077, "best_step": 9, "status": "COMPLETED", "message": null}